localstack_cfn_resource_providers/__init__.py
localstack_cfn_resource_providers/provider_utils.py
localstack_cfn_resource_providers/resource_provider.py
localstack_cfn_resource_providers/iam/__init__.py
localstack_cfn_resource_providers/iam/aws_iam_accesskey.py
localstack_cfn_resource_providers/iam/aws_iam_accesskey.schema.json
localstack_cfn_resource_providers/iam/aws_iam_accesskey_plugin.py
localstack_cfn_resource_providers/iam/aws_iam_group.py
localstack_cfn_resource_providers/iam/aws_iam_group.schema.json
localstack_cfn_resource_providers/iam/aws_iam_group_plugin.py
localstack_cfn_resource_providers/iam/aws_iam_instanceprofile.py
localstack_cfn_resource_providers/iam/aws_iam_instanceprofile.schema.json
localstack_cfn_resource_providers/iam/aws_iam_instanceprofile_plugin.py
localstack_cfn_resource_providers/iam/aws_iam_managedpolicy.py
localstack_cfn_resource_providers/iam/aws_iam_managedpolicy.schema.json
localstack_cfn_resource_providers/iam/aws_iam_managedpolicy_plugin.py
localstack_cfn_resource_providers/iam/aws_iam_policy.py
localstack_cfn_resource_providers/iam/aws_iam_policy.schema.json
localstack_cfn_resource_providers/iam/aws_iam_policy_plugin.py
localstack_cfn_resource_providers/iam/aws_iam_role.py
localstack_cfn_resource_providers/iam/aws_iam_role.schema.json
localstack_cfn_resource_providers/iam/aws_iam_role_plugin.py
localstack_cfn_resource_providers/iam/aws_iam_servicelinkedrole.py
localstack_cfn_resource_providers/iam/aws_iam_servicelinkedrole.schema.json
localstack_cfn_resource_providers/iam/aws_iam_servicelinkedrole_plugin.py
localstack_cfn_resource_providers/iam/aws_iam_user.py
localstack_cfn_resource_providers/iam/aws_iam_user.schema.json
localstack_cfn_resource_providers/iam/aws_iam_user_plugin.py
localstack_cfn_resource_providers-0.1.1.dist-info/LICENSE
localstack_cfn_resource_providers-0.1.1.dist-info/METADATA
localstack_cfn_resource_providers-0.1.1.dist-info/WHEEL
localstack_cfn_resource_providers-0.1.1.dist-info/entry_points.txt
localstack_cfn_resource_providers-0.1.1.dist-info/plux.json
localstack_cfn_resource_providers-0.1.1.dist-info/top_level.txt
localstack_cfn_resource_providers-0.1.1.dist-info/RECORD
